sigma/pipelines/sysmon/__init__.py
sigma/pipelines/sysmon/sysmon.py
pysigma_pipeline_sysmon-1.0.4.dist-info/LICENSE
pysigma_pipeline_sysmon-1.0.4.dist-info/METADATA
pysigma_pipeline_sysmon-1.0.4.dist-info/WHEEL
pysigma_pipeline_sysmon-1.0.4.dist-info/RECORD
