Metadata-Version: 2.1
Name: pysigma-pipeline-sysmon
Version: 1.0.4
Summary: pySigma Sysmon processing pipelines
Home-page: https://github.com/SigmaHQ/pySigma-pipeline-sysmon/
License: LGPL-2.1-only
Author: Thomas Patzke
Author-email: thomas@patzke.org
Requires-Python: >=3.8,<4.0
Classifier: License :: OSI Approved
Classifier: Programming Language :: Python :: 3
Classifier: Programming Language :: Python :: 3.8
Classifier: Programming Language :: Python :: 3.9
Classifier: Programming Language :: Python :: 3.10
Classifier: Programming Language :: Python :: 3.11
Classifier: Programming Language :: Python :: 3.12
Requires-Dist: pysigma (>=0.11,<0.12)
Project-URL: Repository, https://github.com/SigmaHQ/pySigma-pipeline-sysmon/
